{
  "version": 5,
  "analyzer_revision": "white-neutral-guard-v2",
  "model_name": "Jibay_NSFW-1",
  "model_name_sha256": "d9bcc777c8d51af7f0baaeabdfc9101d90626fa4eb895e4fc0757a1b0a4b054b",
  "description": "Bounded local image fingerprints, feature tokens, and rolling moderation statistics.",
  "updated_at": "2026-07-23T10:30:00+00:00",
  "statistics": {
    "total_analyzed": 0,
    "explicit": 0,
    "safe": 0,
    "exact_cache_hits": 0,
    "similarity_matches": 0
  },
  "pattern_counts": {},
  "entries": []
}
